odoo10_addon_account_type_inactive-10.0.1.0.0.99.dev12-py3.8-nspkg.pth
odoo/addons/account_type_inactive/README.rst
odoo/addons/account_type_inactive/__init__.py
odoo/addons/account_type_inactive/__manifest__.py
odoo/addons/account_type_inactive/i18n/account_type_inactive.pot
odoo/addons/account_type_inactive/i18n/es.po
odoo/addons/account_type_inactive/i18n/fr.po
odoo/addons/account_type_inactive/i18n/hr.po
odoo/addons/account_type_inactive/i18n/lt.po
odoo/addons/account_type_inactive/i18n/nl.po
odoo/addons/account_type_inactive/i18n/nl_NL.po
odoo/addons/account_type_inactive/i18n/sl.po
odoo/addons/account_type_inactive/models/__init__.py
odoo/addons/account_type_inactive/models/account_type.py
odoo/addons/account_type_inactive/static/description/icon.png
odoo/addons/account_type_inactive/tests/__init__.py
odoo/addons/account_type_inactive/tests/test_account_type_inactive.py
odoo/addons/account_type_inactive/views/account_type.xml
odoo10_addon_account_type_inactive-10.0.1.0.0.99.dev12.dist-info/METADATA
odoo10_addon_account_type_inactive-10.0.1.0.0.99.dev12.dist-info/WHEEL
odoo10_addon_account_type_inactive-10.0.1.0.0.99.dev12.dist-info/namespace_packages.txt
odoo10_addon_account_type_inactive-10.0.1.0.0.99.dev12.dist-info/top_level.txt
odoo10_addon_account_type_inactive-10.0.1.0.0.99.dev12.dist-info/RECORD
